gnparser/__init__.py
gnparser/libgnparser.dylib
gnparser/libgnparser.so
gnparser-0.1.3.dist-info/METADATA
gnparser-0.1.3.dist-info/WHEEL
gnparser-0.1.3.dist-info/top_level.txt
gnparser-0.1.3.dist-info/RECORD
